binflakes/__init__.py
binflakes-0.dist-info/DESCRIPTION.rst
binflakes-0.dist-info/METADATA
binflakes-0.dist-info/RECORD
binflakes-0.dist-info/WHEEL
binflakes-0.dist-info/entry_points.txt
binflakes-0.dist-info/metadata.json
binflakes-0.dist-info/top_level.txt
