Metadata-Version: 2.0
Name: binflakes
Version: 0
Summary: A catalogue of binary special snowflakes
Home-page: https://github.com/koriakin/binflakes
Author: Marcin Kościelnicki
Author-email: koriakin@0x04.net
License: UNKNOWN
Keywords: binary parser disassembler
Platform: UNKNOWN
Classifier: Development Status :: 1 - Planning
Classifier: License :: OSI Approved :: MIT License
Classifier: Programming Language :: Python :: 3
Classifier: Programming Language :: Python :: 3.5
Classifier: Programming Language :: Python :: 3.6
Provides-Extra: dev
Requires-Dist: check-manifest; extra == 'dev'
Provides-Extra: test
Requires-Dist: coverage; extra == 'test'
